flickr_photostream/__init__.py
flickr_photostream/__main__.py
flickr_photostream/constants.py
flickr_photostream/exception.py
flickr_photostream/flickr_agent.py
flickr_photostream/flickr_api.py
flickr_photostream/flickr_model.py
flickr_photostream/utils.py
flickr_photostream_mirroring-1.0.2.dist-info/LICENSE
flickr_photostream_mirroring-1.0.2.dist-info/METADATA
flickr_photostream_mirroring-1.0.2.dist-info/WHEEL
flickr_photostream_mirroring-1.0.2.dist-info/entry_points.txt
flickr_photostream_mirroring-1.0.2.dist-info/top_level.txt
flickr_photostream_mirroring-1.0.2.dist-info/RECORD
