Metadata-Version: 2.1
Name: flickr-photostream-mirroring
Version: 1.0.2
Summary: Flickr mirroring
Home-page: https://github.com/intek-training-jsc/flickr-mirroring-hoaithu1.git
Author: Thu Hoai
Author-email: hoai.le@f4.intek.edu.vn
License: MIT
Platform: UNKNOWN
Classifier: Programming Language :: Python :: 3
Classifier: License :: OSI Approved :: MIT License
Classifier: Operating System :: OS Independent
Requires-Python: >=3.6
Requires-Dist: certifi (==2020.4.5.1)
Requires-Dist: chardet (==3.0.4)
Requires-Dist: idna (==2.9)
Requires-Dist: langdetect (==1.0.8)
Requires-Dist: requests (==2.23.0)
Requires-Dist: six (==1.14.0)
Requires-Dist: urllib3 (==1.25.9)
